{
    "monsters": [
        {
            "name": "Goblin",
            "hp": 5,
            "melee_attackper": 1,
            "m_hitbase": 51,
            "damage": 1,
            "indoorsight": 4,
            "outdoorsight": 3,
            "movement_description": "You hear the sound of tiny, padded feet and the\n clank of light armor.",
            "behavior": "melee",
            "spawn_zone": "random_room",
            "spawn_min": 3,
            "spawn_max": 3,
            "icon": "G",
            "attackrate": 3
        },
        {
            "name": "Skeleton Archer",
            "hp": 3,
            "ranged_attackper": 1,
            "r_hitbase": 41,
            "damage": 2,
            "indoorsight": 5,
            "outdoorsight": 10,
            "movement_description": "You hear the clatter of dry bones and the release\n of crack of a loosed bow.",
            "behavior": "ranged",
            "spawn_zone": "corridor",
            "spawn_min": 0,
            "spawn_max": 0,
            "icon": "S",
            "attackrate": 5
        }
    ]
}
